kryten_webui/__init__.py
kryten_webui/__main__.py
kryten_webui/config.py
kryten_webui/service.py
kryten_webui-0.1.1.dist-info/entry_points.txt
kryten_webui-0.1.1.dist-info/licenses/LICENSE
kryten_webui-0.1.1.dist-info/METADATA
kryten_webui-0.1.1.dist-info/WHEEL
kryten_webui-0.1.1.dist-info/RECORD
