Metadata-Version: 2.4
Name: kryten-webui
Version: 0.1.1
Summary: Kryten web interface service - provides web dashboard and control panel
License: MIT
License-File: LICENSE
Keywords: cytube,moderation,chat,nats,microservices
Author: Kryten Robot Team
Requires-Python: >=3.10,<4.0
Classifier: Development Status :: 3 - Alpha
Classifier: Intended Audience :: Developers
Classifier: License :: OSI Approved :: MIT License
Classifier: Programming Language :: Python :: 3
Classifier: Programming Language :: Python :: 3.10
Classifier: Programming Language :: Python :: 3.11
Classifier: Programming Language :: Python :: 3.12
Classifier: Programming Language :: Python :: 3.13
Classifier: Programming Language :: Python :: 3.14
Classifier: Topic :: Communications :: Chat
Classifier: Topic :: Software Development :: Libraries :: Python Modules
Requires-Dist: kryten-py (>=0.6.0,<0.7.0)
Project-URL: Documentation, https://github.com/grobertson/kryten-webui/blob/main/README.md
Project-URL: Homepage, https://github.com/grobertson/kryten-webui
Project-URL: Repository, https://github.com/grobertson/kryten-webui
